{
  "icon": {
    "id": "tempad:chronomark"
  },
  "tab": "htimes:htimes",
  "x": -1,
  "y": -4,
  "pages": [
    {
      "type": "datanessence:item",
      "item": {
        "id": "tempad:chronomark"
      },
      "text": {
        "translate": "htimes.data_tablet.pages.chronomark.page1.text"
      }
    },
    {
      "type": "datanessence:crafting",
      "text": {
        "translate": "htimes.data_tablet.pages.chronomark.page2.text"
      },
      "recipes": [
        "tempad:chronomark"
      ]
    },
	{
      "type": "datanessence:crafting",
      "text": {
        "translate": "htimes.data_tablet.pages.chronomark.page3.text"
      },
      "recipes": [
        "tempad:chronomark_clean"
      ]
    }
  ],
  "name": {
    "translate": "htimes.data_tablet.pages.chronomark.name"
  },
  "flavor": {
    "translate": "htimes.data_tablet.pages.chronomark.flavor"
  },
  "parents": [
    "htimes:htimes/chronite"
  ]
}
