{
  "display": {
    "icon": {
      "id": "tempad:chronomark"
    },
    "title": {
      "translate": "htimes.advancement.chronomark.title"
    },
    "description": {
      "translate": "htimes.advancement.chronomark.description"
    },
    "show_toast": false,
    "announce_to_chat": false,
    "hidden": false
  },
  "parent": "htimes:chronite",
  "criteria": {
    "place_chronomark": {
      "trigger": "minecraft:placed_block",
      "conditions": {
        "location": [
          {
            "condition": "minecraft:location_check",
            "predicate": {
              "block": {
                "blocks": "tempad:chronomark"
              }
            }
          }
        ]
      }
    }
  }
}